{
    "items": [
        {"category": "فيلم", "name": "الأب الروحي", "difficulty": "hard"},
        {"category": "فيلم", "name": "تيتانيك", "difficulty": "easy"},
        {"category": "مسرحية", "name": "البؤساء", "difficulty": "hard"},
        {"category": "فيلم", "name": "العراف", "difficulty": "medium"},
        {"category": "مسلسل", "name": "الوصية", "difficulty": "medium"},
        {"category": "فيلم", "name": "ريا وسكينة", "difficulty": "easy"},
        {"category": "مسرحية", "name": "مدرسة المشاغبين", "difficulty": "easy"},
        {"category": "فيلم", "name": "العيال كبرت", "difficulty": "easy"},
        {"category": "مسلسل", "name": "شمس الزناتي", "difficulty": "medium"},
        {"category": "مسرحية", "name": "الناظر", "difficulty": "medium"},
        {"category": "مسرحية", "name": "المتزوج", "difficulty": "medium"},
        {"category": "فيلم", "name": "الكيت كات", "difficulty": "hard"},
        {"category": "فيلم", "name": "باب الحديد", "difficulty": "hard"},
        {"category": "فيلم", "name": "يوم من عمري", "difficulty": "medium"},
        {"category": "فيلم", "name": "صلاح الدين", "difficulty": "medium"},
        {"category": "مسلسل", "name": "الحفيد", "difficulty": "easy"},
        {"category": "مسلسل", "name": "زيزينيا", "difficulty": "medium"},
        {"category": "فيلم", "name": "الكرنك", "difficulty": "hard"},
        {"category": "فيلم", "name": "شيء من الخوف", "difficulty": "hard"},
        {"category": "فيلم", "name": "الأرض", "difficulty": "hard"},
        {"category": "فيلم", "name": "طباخ الريس", "difficulty": "easy"},
        {"category": "فيلم", "name": "كده رضا", "difficulty": "easy"},
        {"category": "مسلسل", "name": "رأفت الهجان", "difficulty": "medium"},
        {"category": "مسلسل", "name": "ليالي الحلمية", "difficulty": "medium"},
        {"category": "فيلم", "name": "الإرهاب والكباب", "difficulty": "medium"},
        {"category": "فيلم", "name": "فول الصين العظيم", "difficulty": "easy"}
    ]
}
